ocpdet/CUSUM.py
ocpdet/EWMA.py
ocpdet/NeuralNetwork.py
ocpdet/TwoSample.py
ocpdet/__init__.py
ocpdet-0.0.6.dist-info/LICENSE
ocpdet-0.0.6.dist-info/METADATA
ocpdet-0.0.6.dist-info/WHEEL
ocpdet-0.0.6.dist-info/top_level.txt
ocpdet-0.0.6.dist-info/RECORD
