Metadata-Version: 2.1
Name: ocpdet
Version: 0.0.6
Summary: A Python package for online changepoint detection, implementing state-of-the-art algorithms and a novel approach.
Home-page: https://github.com/vkhamesi/ocpdet
Author: Victor Khamesi
Author-email: victor.khamesi21@imperial.ac.uk
Classifier: Programming Language :: Python :: 3
Classifier: License :: OSI Approved :: BSD License
Classifier: Operating System :: OS Independent
Requires-Python: >=3.6
License-File: LICENSE
Requires-Dist: numpy
Requires-Dist: tqdm
Requires-Dist: tensorflow
Requires-Dist: scipy
